Metadata-Version: 1.0
Name: gbdist
Version: 0.1
Summary: Gaussian distributions
Home-page: UNKNOWN
Author: Rahul Khairnar
Author-email: UNKNOWN
License: UNKNOWN
Platform: UNKNOWN
